am4_prices/__init__.py
am4_prices/api.py
am4_prices/cli.py
am4_prices/models.py
am4_prices/ui.py
am4_prices-0.1.0.dist-info/METADATA
am4_prices-0.1.0.dist-info/WHEEL
am4_prices-0.1.0.dist-info/entry_points.txt
am4_prices-0.1.0.dist-info/licenses/LICENSE
am4_prices-0.1.0.dist-info/RECORD
