Metadata-Version: 2.4
Name: am4-prices
Version: 0.1.0
Summary: A sleek CLI client for Airline Manager 4 Fuel/CO2 prices
Project-URL: Homepage, https://github.com/barcister/am4-helper-cli
Project-URL: Repository, https://github.com/barcister/am4-helper-cli
Project-URL: Issues, https://github.com/barcister/am4-helper-cli/issues
Author: AM4 Prices Contributors
License: MIT
License-File: LICENSE
Keywords: airline-manager,am4,cli,co2,fuel-prices,tui
Classifier: Development Status :: 4 - Beta
Classifier: Environment :: Console
Classifier: Intended Audience :: End Users/Desktop
Classifier: License :: OSI Approved :: MIT License
Classifier: Operating System :: OS Independent
Classifier: Programming Language :: Python :: 3
Classifier: Programming Language :: Python :: 3.9
Classifier: Programming Language :: Python :: 3.10
Classifier: Programming Language :: Python :: 3.11
Classifier: Programming Language :: Python :: 3.12
Classifier: Topic :: Games/Entertainment
Classifier: Topic :: Utilities
Requires-Python: >=3.9
Requires-Dist: httpx>=0.27.0
Requires-Dist: pydantic>=2.6.0
Requires-Dist: python-dateutil>=2.8.2
Requires-Dist: rich>=13.7.0
Requires-Dist: typer>=0.12.0
Provides-Extra: dev
Requires-Dist: mypy>=1.8.0; extra == 'dev'
Requires-Dist: pytest-cov>=4.1.0; extra == 'dev'
Requires-Dist: pytest>=8.0.0; extra == 'dev'
Requires-Dist: ruff>=0.2.0; extra == 'dev'
